pyqt_units/ConglomerateWidgets.py
pyqt_units/CurrentUnitSetter.py
pyqt_units/MeasurementDatabase.py
pyqt_units/MeasurementWidgets.py
pyqt_units/SelectionMenu.py
pyqt_units/UnitComboDelegate.py
pyqt_units/__init__.py
pyqt_units/models.py
pyqt_units/measurements/measurements_root.db
pyqt_units-4.0.dist-info/LICENSE
pyqt_units-4.0.dist-info/METADATA
pyqt_units-4.0.dist-info/WHEEL
pyqt_units-4.0.dist-info/top_level.txt
pyqt_units-4.0.dist-info/RECORD
